{
    "title": "Test Application",
    "description": "A GUI-based test application",
    "container": "test",
    "features": [],
    "databases": {
        "@": [
            "##FRAMEWORK"
        ]
    },
    "webx" : {
        "TestApp": {
            "className": "WebApp",
            "websocket": true,
            "permissions": [],
            "client": ["./client"],
            "server": ["./server"],
            "cssSheets": [ "module.css" ],
            "defaultLanguage": "en",
            "text": ["textAppText.js"],
            "homeView": "HomeView"
        }
    }
}
